README.rst
setup.py
jrtzcloud_python_sdk_consensus.egg-info/PKG-INFO
jrtzcloud_python_sdk_consensus.egg-info/SOURCES.txt
jrtzcloud_python_sdk_consensus.egg-info/dependency_links.txt
jrtzcloud_python_sdk_consensus.egg-info/requires.txt
jrtzcloud_python_sdk_consensus.egg-info/top_level.txt
jrtzcloudsdkconsensus/__init__.py
jrtzcloudsdkconsensus/v20191119/__init__.py
jrtzcloudsdkconsensus/v20191119/consensus_client.py
jrtzcloudsdkconsensus/v20191119/models.py