Metadata-Version: 1.1
Name: jrtzcloud-python-sdk-consensus
Version: 1.1.0
Summary: The consensus module of JrtzCloud Python sdk.
Home-page: https://github.com/jrtzcloud/jrtzcloud-openapi-python-sdk
Author: JrtzCloud
Author-email: pantj@investoday.com.cn
License: Apache
Keywords: jrtzcloud,sdk,consensus
Platform: any
Classifier: Development Status :: 4 - Beta
Classifier: Intended Audience :: Developers
Classifier: License :: OSI Approved :: Apache Software License
Classifier: Programming Language :: Python
Classifier: Programming Language :: Python :: 2.6
Classifier: Programming Language :: Python :: 2.7
Classifier: Programming Language :: Python :: 3
Classifier: Programming Language :: Python :: 3.3
Classifier: Programming Language :: Python :: 3.4
Classifier: Programming Language :: Python :: 3.5
Classifier: Programming Language :: Python :: 3.6
Classifier: Topic :: Software Development
